.gitignore
.travis.yml
LICENSE
README.md
requirements.txt
setup.py
sample_app/__init__.py
sample_app/simple.py
sanic_aiopylimit/decorators.py
sanic_aiopylimit/limit.py
sanic_aiopylimit.egg-info/PKG-INFO
sanic_aiopylimit.egg-info/SOURCES.txt
sanic_aiopylimit.egg-info/dependency_links.txt
sanic_aiopylimit.egg-info/requires.txt
sanic_aiopylimit.egg-info/top_level.txt
tests/__init__.py
tests/test_simple.py
tests/test_unit.py