Metadata-Version: 1.0
Name: sanic-aiopylimit
Version: 0.2
Summary: A utlity package to help with distributed rate limiting with sanic and redis
Home-page: https://github.com/dmarkey/sanic-aiopylimit
Author: David Markey
Author-email: david@dmarkey.com
License: UNKNOWN
Keywords: rate limiting,throttle,redis,asyncio,sanic
Platform: UNKNOWN
